Metadata-Version: 2.1
Name: image-processing-pkg-vleite
Version: 0.0.1
Summary: Duplicated project to learn how work packages in Python
Home-page: https://github.com/vitoleite/image_processing_dio
Author: vitor_leite
Author-email: vitorleite5@outlook.com
License: UNKNOWN
Platform: UNKNOWN
Requires-Python: >=3.8
Requires-Dist: numpy
Requires-Dist: scikit-image
Requires-Dist: matplotlib
